viennals-5.5.0.dist-info/RECORD
viennals-5.5.0.dist-info/WHEEL
viennals-5.5.0.dist-info/METADATA
viennals-5.5.0.dist-info/licenses/LICENSE
viennals.libs/libvtkIOLegacy-9.3.dylib
viennals.libs/libvtkverdict-9.3.dylib
viennals.libs/libvtkexpat-9.3.dylib
viennals.libs/libvtkfreetype-9.3.dylib
viennals.libs/libvtkFiltersCore-9.3.dylib
viennals.libs/libvtkCommonMath-9.3.dylib
viennals.libs/libvtkRenderingAnnotation-9.3.dylib
viennals.libs/libvtkDICOMParser-9.3.dylib
viennals.libs/libvtkParallelDIY-9.3.dylib
viennals.libs/libvtkFiltersSources-9.3.dylib
viennals.libs/libvtkIOXML-9.3.dylib
viennals.libs/libvtkloguru-9.3.dylib
viennals.libs/libvtkImagingSources-9.3.dylib
viennals.libs/libvtkIOCore-9.3.dylib
viennals.libs/libvtkCommonColor-9.3.dylib
viennals.libs/libvtkRenderingCore-9.3.dylib
viennals.libs/libvtkFiltersStatistics-9.3.dylib
viennals.libs/libvtkmetaio-9.3.dylib
viennals.libs/libvtkRenderingHyperTreeGrid-9.3.dylib
viennals.libs/libvtkFiltersGeometry-9.3.dylib
viennals.libs/libvtkglew-9.3.dylib
viennals.libs/libvtkCommonSystem-9.3.dylib
viennals.libs/libvtktiff-9.3.dylib
viennals.libs/libvtkRenderingFreeType-9.3.dylib
viennals.libs/libvtkkissfft-9.3.dylib
viennals.libs/libvtkImagingCore-9.3.dylib
viennals.libs/libvtkdoubleconversion-9.3.dylib
viennals.libs/libvtkpugixml-9.3.dylib
viennals.libs/libvtkfmt-9.3.dylib
viennals.libs/libvtkCommonComputationalGeometry-9.3.dylib
viennals.libs/libvtkCommonTransforms-9.3.dylib
viennals.libs/libvtkInteractionStyle-9.3.dylib
viennals.libs/libvtkCommonCore-9.3.dylib
viennals.libs/libvtkFiltersHyperTree-9.3.dylib
viennals.libs/libvtkjpeg-9.3.dylib
viennals.libs/libvtkCommonMisc-9.3.dylib
viennals.libs/libvtkFiltersGeneral-9.3.dylib
viennals.libs/libvtkFiltersHybrid-9.3.dylib
viennals.libs/libvtkImagingColor-9.3.dylib
viennals.libs/libvtklz4-9.3.dylib
viennals.libs/libvtkRenderingOpenGL2-9.3.dylib
viennals.libs/libvtkCommonDataModel-9.3.dylib
viennals.libs/libvtkIOImage-9.3.dylib
viennals.libs/libvtkIOXMLParser-9.3.dylib
viennals.libs/libvtkFiltersExtraction-9.3.dylib
viennals.libs/libvtkRenderingUI-9.3.dylib
