Metadata-Version: 2.2
Name: ViennaLS
Version: 5.5.0
Summary: A high performance sparse level set library
License: Copyright (c) 2015-2025      Institute for Microelectronics, TU Wien.
Project-URL: Homepage, https://viennatools.github.io/ViennaLS/
Project-URL: Documentation, https://viennatools.github.io/ViennaLS/
Project-URL: Repository, https://github.com/ViennaTools/ViennaLS
Project-URL: Issues, https://github.com/ViennaTools/ViennaLS/issues
